moageet.py
setup.cfg
setup.py
moageet.egg-info/PKG-INFO
moageet.egg-info/SOURCES.txt
moageet.egg-info/dependency_links.txt
moageet.egg-info/requires.txt
moageet.egg-info/top_level.txt