Metadata-Version: 1.0
Name: moageet
Version: 1.0.4
Summary: Moageet al salah
Home-page: UNKNOWN
Author: Mansour A Almansour
Author-email: almansour2345@gmail.com
License: GPL-3.0
Platform: UNKNOWN
